soga_sora2/__init__.py
soga_sora2/cli.py
soga_sora2-0.1.1.dist-info/METADATA
soga_sora2-0.1.1.dist-info/WHEEL
soga_sora2-0.1.1.dist-info/entry_points.txt
soga_sora2-0.1.1.dist-info/top_level.txt
soga_sora2-0.1.1.dist-info/RECORD
