Metadata-Version: 2.4
Name: soga-sora2
Version: 0.1.1
Author-email: Your Name <your.email@example.com>
Classifier: Programming Language :: Python :: 3
Classifier: Operating System :: OS Independent
Requires-Python: >=3.12
Requires-Dist: pandas>=2.3.3
Requires-Dist: requests>=2.32.5
Provides-Extra: test
